UltimateEdgarParser/UltimateEdgarParser.py
UltimateEdgarParser/__init__.py
UltimateEdgarParser-0.1.2.dist-info/METADATA
UltimateEdgarParser-0.1.2.dist-info/WHEEL
UltimateEdgarParser-0.1.2.dist-info/top_level.txt
UltimateEdgarParser-0.1.2.dist-info/RECORD
