Metadata-Version: 2.1
Name: UltimateEdgarParser
Version: 0.1.2
Summary: Pulling Edgar 10Q Files
Author: Saeed Shadkam
Author-email: <shadkam@ualberta.ca
License: UNKNOWN
Keywords: python,Finance,EDGAR,SEC
Platform: UNKNOWN
Classifier: Development Status :: 1 - Planning
Classifier: Intended Audience :: Developers
Classifier: Programming Language :: Python :: 3
Classifier: Operating System :: Unix
Classifier: Operating System :: MacOS :: MacOS X
Classifier: Operating System :: Microsoft :: Windows
Requires-Dist: pandas
